visread/__init__.py
visread/process.py
visread/process_casa.py
visread/scatter.py
visread/scatter_casa.py
visread/utils.py
visread/visread_version.py
visread/visualization.py
visread/visualization_casa.py
visread-0.0.5.dist-info/METADATA
visread-0.0.5.dist-info/WHEEL
visread-0.0.5.dist-info/licenses/LICENSE
visread-0.0.5.dist-info/RECORD
